zinv/__init__.py
zinv/modules/__init__.py
zinv/modules/analyse.py
zinv/modules/resume.py
zinv/modules/collectors/HDF5.py
zinv/modules/collectors/__init__.py
zinv/modules/readers/CertifiedLumiChecker.py
zinv/modules/readers/CollectionCreator.py
zinv/modules/readers/EventFunctions.py
zinv/modules/readers/EventTools.py
zinv/modules/readers/GenBosonProducer.py
zinv/modules/readers/JecVariations.py
zinv/modules/readers/LHEPartAssigner.py
zinv/modules/readers/ObjectCrossCleaning.py
zinv/modules/readers/ObjectFunctions.py
zinv/modules/readers/ScribblerWrapper.py
zinv/modules/readers/SelectionProducer.py
zinv/modules/readers/SkimCollections.py
zinv/modules/readers/TriggerChecker.py
zinv/modules/readers/WeightBTagging.py
zinv/modules/readers/WeightMetTrigger.py
zinv/modules/readers/WeightMetTrigger2.py
zinv/modules/readers/WeightObjects.py
zinv/modules/readers/WeightPdfScale.py
zinv/modules/readers/WeightPileup.py
zinv/modules/readers/WeightPreFiring.py
zinv/modules/readers/WeightQcdEwk.py
zinv/modules/readers/WeightXsLumi.py
zinv/modules/readers/__init__.py
zinv/utils/AwkwardOps.py
zinv/utils/Geometry.py
zinv/utils/Lambda.py
zinv/utils/NumbaFuncs.py
zinv/utils/__init__.py
zinv/utils/build_sequence.py
zinv/utils/cache_funcs.py
zinv/utils/datasets.py
zinv/utils/gittools.py
zinv/utils/grouped_run.py
zinv_analysis-0.3.2.data/scripts/zinv_analyse.py
zinv_analysis-0.3.2.data/scripts/zinv_resume.py
zinv_analysis-0.3.2.dist-info/LICENSE
zinv_analysis-0.3.2.dist-info/METADATA
zinv_analysis-0.3.2.dist-info/WHEEL
zinv_analysis-0.3.2.dist-info/top_level.txt
zinv_analysis-0.3.2.dist-info/RECORD
