Metadata-Version: 2.1
Name: zinv-analysis
Version: 0.3.2
Summary: AlphaTwirl + uproot for the Z inv. width analysis
Home-page: https://github.com/shane-breeze/zinv-analysis
Author: Shane Breeze
Author-email: sdb15@ic.ac.uk
License: UNKNOWN
Platform: UNKNOWN
Classifier: Programming Language :: Python :: 3
Classifier: License :: OSI Approved :: MIT License
Classifier: Operating System :: OS Independent
Classifier: Topic :: Software Development :: Libraries :: Python Modules
Classifier: Topic :: Utilities
Classifier: Development Status :: 3 - Alpha
Requires-Dist: alphatwirl (>=0.23.2)
Requires-Dist: atuproot (>=0.1.13)
Requires-Dist: awkward (>=0.8.11)
Requires-Dist: awkward-numba (>=0.8.11)
Requires-Dist: cachetools (>=3.1.0)
Requires-Dist: icc-rt (>=2019.0)
Requires-Dist: intel-openmp (>=2019.0)
Requires-Dist: numba (>=0.42.1)
Requires-Dist: numpy (>=1.16.2)
Requires-Dist: oyaml (>=0.8)
Requires-Dist: pandas (>=0.24.1)
Requires-Dist: pysge (>=0.1.3)
Requires-Dist: scipy (>=1.3.1)
Requires-Dist: six (>=1.12.0)
Requires-Dist: subprocess32 (>=3.5.3)
Requires-Dist: tabulate (>=0.8.3)
Requires-Dist: tqdm (>=4.31.1)
Requires-Dist: uproot (>=3.4.9)
Requires-Dist: uproot-methods (>=0.4.3)
